README.md
setup.cfg
setup.py
jiofi/__init__.py
jiofi/jiofi.py
jiofi.egg-info/PKG-INFO
jiofi.egg-info/SOURCES.txt
jiofi.egg-info/dependency_links.txt
jiofi.egg-info/entry_points.txt
jiofi.egg-info/requires.txt
jiofi.egg-info/top_level.txt