Metadata-Version: 2.1
Name: jiofi
Version: 0.1.3
Summary: A Command Line Interface to get stats about your Jiofi.
Home-page: https://github.com/athul/jiofi-cli
Author: Athul Cyriac Ajay
Author-email: athul8720@gmail.com
License: MIT
Platform: UNKNOWN
Classifier: License :: OSI Approved :: MIT License
Classifier: Programming Language :: Python :: 3.6
Requires-Python: >=3.6.0
